countparticles.py
countparticles-1.3.dist-info/LICENSE
countparticles-1.3.dist-info/METADATA
countparticles-1.3.dist-info/WHEEL
countparticles-1.3.dist-info/entry_points.txt
countparticles-1.3.dist-info/top_level.txt
countparticles-1.3.dist-info/RECORD
